aime_xai/__init__.py
aime_xai/core.py
aime_xai-1.1.0.dist-info/licenses/LICENSE.txt
aime_xai-1.1.0.dist-info/METADATA
aime_xai-1.1.0.dist-info/WHEEL
aime_xai-1.1.0.dist-info/top_level.txt
aime_xai-1.1.0.dist-info/RECORD
