Metadata-Version: 2.4
Name: aime-xai
Version: 1.1.0
Summary: Approximate Inverse Model Explanations (AIME): unified global/local importance for XAI
License: LicenseRef-AIME-Academic-NonCommercial
Classifier: Programming Language :: Python :: 3
Classifier: License :: Other/Proprietary License
Classifier: Operating System :: OS Independent
Classifier: Topic :: Scientific/Engineering :: Artificial Intelligence
License-File: LICENSE.txt
Dynamic: classifier
Dynamic: description
Dynamic: description-content-type
Dynamic: license
Dynamic: license-file
Dynamic: summary
